PASS/__init__.py
PASS/_version.py
PASS/apps/L1_L2_probability_statistics.py
PASS/apps/__init__.py
PASS/apps/cli.py
PASS/apps/make_config.py
PASS/apps/minimum_battery_capacitance.py
PASS/apps/multiple_trajectory.py
PASS/apps/net_power_production.py
PASS/apps/optimal_tilt.py
PASS/apps/phase_space.py
PASS/apps/plot_trajectory.py
PASS/apps/power_consumption.py
PASS/apps/power_production.py
PASS/apps/single_trajectory.py
PASS/apps/traj_stats.py
PASS/config/PASS_config.toml
PASS/config/__init__.py
PASS/config/config.py
PASS/config/load_config.py
PASS/data/__init__.py
PASS/data/simulated_trajectories.zip
PASS/general_framework/__init__.py
PASS/general_framework/general_classes.py
PASS/general_framework/power_status.py
PASS/general_framework/power_system_capacitance.py
PASS/power_consumption/__init__.py
PASS/power_consumption/observation_period_2.py
PASS/power_consumption/power_capacitance.py
PASS/power_consumption/power_consumption_classes.py
PASS/power_consumption/read_astro.py
PASS/power_consumption/sun_moon_cuts.py
PASS/solar_production/__init__.py
PASS/solar_production/optimal_tilt_angle.py
PASS/solar_production/solar_elevation_angle.py
PASS/solar_production/solar_production_classes.py
PASS/visualization/__init__.py
PASS/visualization/old_plotting_funcs.py
PASS/visualization/plotting_funcs.py
PASS/visualization/spp_plots.py
PASS/visualization/style/__init__.py
PASS/visualization/style/default.py
PASS/visualization/style/document.py
PASS/visualization/style/document_nw.py
PASS/visualization/style/plot.py
PASS/visualization/style/presentation.py
PASS/visualization/style/watermark.py
PASS/visualization/style/styles/document.mplstyle
PASS/visualization/style/styles/document_latex.mplstyle
PASS/visualization/style/styles/presentation.mplstyle
bipass-1.0.0.post0.dist-info/licenses/LICENSE
bipass-1.0.0.post0.dist-info/METADATA
bipass-1.0.0.post0.dist-info/WHEEL
bipass-1.0.0.post0.dist-info/entry_points.txt
bipass-1.0.0.post0.dist-info/top_level.txt
bipass-1.0.0.post0.dist-info/RECORD
