Metadata-Version: 2.4
Name: bipass
Version: 1.0.0.post0
Summary: Balloon Instrumentation Power system Analysis and Simulation Software
Author: Julia Burton
Author-email: julia_burton@mines.edu
License: BSD-3-Clause-Clear
Classifier: Development Status :: 4 - Beta
Classifier: Intended Audience :: Science/Research
Classifier: License :: OSI Approved :: BSD License
Classifier: Programming Language :: Python :: 3
Classifier: Programming Language :: Python :: 3.13
Classifier: Programming Language :: Python :: 3.14
Requires-Python: >=3.13
License-File: LICENSE
Requires-Dist: matplotlib
Requires-Dist: numpy
Requires-Dist: pandas
Requires-Dist: astropy
Requires-Dist: pysolar
Requires-Dist: pyarrow
Requires-Dist: click
Requires-Dist: tqdm
Requires-Dist: toml
Requires-Dist: pytest
Dynamic: license-file
